{
  "id": "faroe-svalbard-arctic-expedition-22d",
  "mode": "inspiration",
  "modePrimary": "地貌与星空（Polar）",
  "modeTags": "海鸟崖, 观鲸, 多地串联",
  "title": "北极法罗+斯瓦尔巴德群岛深度探索之旅（22天）",
  "coverImage": "https://source.unsplash.com/1600x900/?faroe,islands,svalbard,arctic",
  "location": "法罗群岛 · 斯瓦尔巴德群岛 · 丹麦 · 挪威",
  "duration": 22,
  "summary": "一次连接北大西洋秘境与北极熊王国的深度探险，从法罗群岛的田园诗境到斯瓦尔巴德的极致荒原，体验双重视觉与文化震撼。",
  "description": "22天北极双区域深度行程，涵盖法罗群岛的鸟类天堂、海上奇观、村庄文化，以及斯瓦尔巴德群岛的环游探险，寻觅北极熊、巡游超级冰川，体验最纯正的北极荒野。",
  "coreInsight": "8月是法罗群岛与斯瓦尔巴德群岛的最佳访问季。法罗群岛万物生机勃勃，海鹦鹉活跃；斯瓦尔巴德海冰融化，通行条件佳，是观测北极熊与巡游超级冰川的黄金窗口。",
  "safetyNotices": {
    "en": "Faroe Islands weather is highly changeable; itinerary may adjust. Svalbard itinerary is a true expedition, entirely dependent on weather, ice, and wildlife. Strictly follow safety protocols in polar bear country.",
    "zh-cn": "法罗群岛天气多变，行程可能调整。斯瓦尔巴德行程为真正的探险，路线完全由天气、冰况和野生动物决定。在北极熊出没区域，必须严格遵守探险队安全规定。"
  },
  "journeyBackground": [
    {
      "text": "法罗群岛由18个火山岛组成，以陡峭的悬崖、绿色山丘和丰富的海鸟群落闻名，是摄影家和自然爱好者的天堂。",
      "order": 1
    },
    {
      "text": "斯瓦尔巴德群岛是北极熊王国，其数量超过居民。运营方拥有19年内30次探访的丰富经验，极大提升了观测北极熊的概率。",
      "order": 2
    }
  ],
  "personaProfile": {
    "type": "深度自然与文化探索者",
    "motivation": "一次性集齐北大西洋的隐世美景与北极的顶级野生动物，完成一次从温带到寒带的完整自然梯度体验",
    "travelRhythm": "法罗段：固定行程与徒步；斯瓦尔巴德段：弹性探险；中间都市段：缓冲休整",
    "cognitiveNeed": "深入了解法罗群岛的维京历史与生态、斯瓦尔巴德的北极生态系统与冰川学",
    "foodPreference": "体验法罗群岛的北欧海鲜与斯瓦尔巴德的船餐",
    "dominantEmotion": "持续的发现感与震撼",
    "socialPreference": "乐于在小团体中交流，享受与探险家和当地人的互动"
  },
  "journeyDesign": {
    "slug": "faroe-svalbard-arctic-expedition-22d",
    "socialMode": "法罗段小团体文化探索，斯瓦尔巴德段探险船集体科考模式",
    "coreInsight": "北大西洋秘境文化 + 北极熊王国荒野探险",
    "mentalFlowStages": {
      "summon": {
        "theme": "哥本哈根，北欧风情",
        "activities": [
          "哥本哈根抵达与适应"
        ],
        "emotionalGoal": "开启北欧秘境与北极探险的期待",
        "symbolicElement": "北欧设计"
      },
      "awakening": {
        "theme": "驶向北极",
        "activities": [
          "奥斯陆文化体验",
          "朗伊尔城登船"
        ],
        "emotionalGoal": "感受从温带文明向北极荒野的过渡与升华"
      },
      "reflection": {
        "theme": "法罗群岛，维京后花园",
        "activities": [
          "托尔斯港历史漫步",
          "米基内斯岛观鸟",
          "黄金圈村庄探访"
        ],
        "emotionalGoal": "沉浸于北大西洋的田园诗境与狂野海岸"
      },
      "transformation": {
        "theme": "告别冰原，传奇永驻",
        "activities": [
          "下船返航",
          "奥斯陆返程"
        ],
        "emotionalGoal": "将双岛的震撼记忆内化为毕生的宝贵财富"
      },
      "internalization": {
        "theme": "斯瓦尔巴德，北极熊王国",
        "activities": [
          "穿越北纬80度",
          "寻觅北极熊",
          "巡游超级冰川与冰瀑布"
        ],
        "emotionalGoal": "亲历北极荒野的原始力量与生命奇迹"
      }
    },
    "symbolicElements": [
      "海鹦鹉",
      "海上悬湖",
      "北极熊",
      "超级冰川",
      "维京历史"
    ],
    "psychologicalFlow": [
      "北欧都市启程",
      "法罗群岛仙境漫游",
      "航向北极门户",
      "斯瓦尔巴德荒野觉醒",
      "满载回忆归程"
    ],
    "recommendedRhythm": "法罗段日间户外探索，斯瓦尔巴德段全天候弹性探险"
  },
  "mentalFlowStages": {
    "summon": {
      "theme": "哥本哈根，北欧风情",
      "activities": [
        "哥本哈根抵达与适应"
      ],
      "emotionalGoal": "开启北欧秘境与北极探险的期待",
      "symbolicElement": "北欧设计"
    },
    "awakening": {
      "theme": "驶向北极",
      "activities": [
        "奥斯陆文化体验",
        "朗伊尔城登船"
      ],
      "emotionalGoal": "感受从温带文明向北极荒野的过渡与升华"
    },
    "reflection": {
      "theme": "法罗群岛，维京后花园",
      "activities": [
        "托尔斯港历史漫步",
        "米基内斯岛观鸟",
        "黄金圈村庄探访"
      ],
      "emotionalGoal": "沉浸于北大西洋的田园诗境与狂野海岸"
    },
    "transformation": {
      "theme": "告别冰原，传奇永驻",
      "activities": [
        "下船返航",
        "奥斯陆返程"
      ],
      "emotionalGoal": "将双岛的震撼记忆内化为毕生的宝贵财富"
    },
    "internalization": {
      "theme": "斯瓦尔巴德，北极熊王国",
      "activities": [
        "穿越北纬80度",
        "寻觅北极熊",
        "巡游超级冰川与冰瀑布"
      ],
      "emotionalGoal": "亲历北极荒野的原始力量与生命奇迹"
    }
  },
  "tasks": [
    {
      "id": "task_auto_visa_schengen",
      "links": [
        {
          "url": "https://www.schengenvisainfo.com/",
          "name": "申根签证信息"
        }
      ],
      "title": "确认申根签证有效性（适用于丹麦及挪威）",
      "autoKey": "documents_schengen_visa",
      "category": "documents",
      "destination": "丹麦/挪威",
      "autoGenerated": true
    },
    {
      "id": "task_auto_hiking_photography_gear",
      "title": "准备专业徒步与摄影装备：防水登山鞋、防风防水外套、长焦镜头、望远镜",
      "autoKey": "gear_hiking_photography",
      "category": "gear",
      "autoGenerated": true
    },
    {
      "id": "task_auto_bear_safety",
      "links": [
        {
          "url": "https://www.sysselmesteren.no/en/visitors/",
          "name": "斯瓦尔巴德总督府游客指南"
        }
      ],
      "title": "学习并理解北极熊安全守则",
      "autoKey": "safety_polar_bear",
      "category": "safety",
      "autoGenerated": true
    }
  ],
  "days": [
    {
      "dayNumber": 1,
      "title": "中国 -> 哥本哈根（夜宿航班）",
      "summary": "搭乘国际航班飞往丹麦首都哥本哈根。",
      "detailsJson": null,
      "timeSlots": [
        {
          "sequence": 1,
          "durationHours": 24,
          "durationMinutes": 1440,
          "type": "transport",
          "title": "机场集合与飞行",
          "activityHighlights": {
            "text": "办理登机手续，开启北欧与北极之旅。"
          },
          "locationJson": {
            "name": "国际航班"
          },
          "detailsJson": {
            "location": "国际航班",
            "transport": {
              "mode": "flight"
            },
            "durationHours": 24
          }
        }
      ]
    },
    {
      "dayNumber": 2,
      "title": "抵达哥本哈根",
      "summary": "抵达哥本哈根，入住酒店调整时差。",
      "detailsJson": null,
      "timeSlots": [
        {
          "sequence": 1,
          "durationHours": 2,
          "durationMinutes": 120,
          "type": "arrival",
          "title": "抵达与入住",
          "activityHighlights": {
            "text": "导游接机，前往市区酒店办理入住。"
          },
          "locationJson": {
            "name": "哥本哈根酒店"
          },
          "detailsJson": {
            "location": "哥本哈根酒店",
            "transport": {
              "mode": "private_transfer"
            },
            "durationHours": 2
          }
        }
      ]
    },
    {
      "dayNumber": 3,
      "title": "飞往北大西洋秘境：法罗群岛",
      "summary": "搭乘航班飞往法罗群岛，抵达首府托尔斯港。",
      "detailsJson": null,
      "timeSlots": [
        {
          "sequence": 1,
          "durationHours": 2,
          "durationMinutes": 120,
          "type": "transport",
          "title": "飞往法罗群岛",
          "activityHighlights": null,
          "locationJson": {
            "name": "哥本哈根 -> 沃格岛机场"
          },
          "detailsJson": {
            "location": "哥本哈根 -> 沃格岛机场",
            "transport": {
              "mode": "flight"
            },
            "durationHours": 2
          }
        },
        {
          "sequence": 2,
          "durationHours": 3,
          "durationMinutes": 180,
          "type": "culture",
          "title": "托尔斯港历史探索",
          "activityHighlights": {
            "text": "游览港口、彩色屋顶的老城区和历史仓库，了解维京历史。"
          },
          "scenicIntro": "托尔斯港是法罗群岛的政治文化中心，充满北欧风情。",
          "locationJson": {
            "name": "托尔斯港"
          },
          "detailsJson": {
            "location": "托尔斯港",
            "durationHours": 3
          }
        }
      ]
    },
    {
      "dayNumber": 4,
      "title": "米基内斯岛观鸟之旅",
      "summary": "乘船前往海鸟天堂米基内斯岛，邂逅海鹦鹉。",
      "detailsJson": null,
      "timeSlots": [
        {
          "sequence": 1,
          "durationHours": 1.5,
          "durationMinutes": 90,
          "type": "transport",
          "title": "乘船前往米基内斯岛",
          "activityHighlights": null,
          "locationJson": {
            "name": "托尔斯港 -> 米基内斯岛"
          },
          "detailsJson": {
            "location": "托尔斯港 -> 米基内斯岛",
            "transport": {
              "mode": "ferry"
            },
            "durationHours": 1.5
          }
        },
        {
          "sequence": 2,
          "durationHours": 4,
          "durationMinutes": 240,
          "type": "nature",
          "title": "米基内斯岛徒步与观鸟",
          "activityHighlights": {
            "text": "寻找海鹦鹉洞穴，观赏鸬鹚、海鸠等在悬崖上筑巢，参观古老灯塔。"
          },
          "scenicIntro": "米基内斯岛是北大西洋最重要的鸟类保护区之一。",
          "locationJson": {
            "name": "米基内斯岛"
          },
          "detailsJson": {
            "localTip": "路径可能泥泞，务必穿着防水防滑的徒步鞋。",
            "location": "米基内斯岛",
            "durationHours": 4
          }
        }
      ]
    },
    {
      "dayNumber": 5,
      "title": "黄金圈村庄巡礼",
      "summary": "探访串联起三个最隐秘村庄的黄金圈，感受淳朴民风。",
      "detailsJson": null,
      "timeSlots": [
        {
          "sequence": 1,
          "durationHours": 4,
          "durationMinutes": 240,
          "type": "culture",
          "title": "隐秘村庄探访",
          "activityHighlights": {
            "text": "拜访三个与世隔绝的田园诗般村庄，与当地居民交流，感受传统生活。"
          },
          "scenicIntro": "这些村庄人口稀少，保留着最传统的法罗生活方式。",
          "locationJson": {
            "name": "法罗群岛北部"
          },
          "detailsJson": {
            "location": "法罗群岛北部",
            "durationHours": 4
          }
        },
        {
          "sequence": 2,
          "durationHours": 1,
          "durationMinutes": 60,
          "type": "nature",
          "title": "Fossá瀑布观赏",
          "activityHighlights": {
            "text": "欣赏法罗群岛最大、最壮观的瀑布。"
          },
          "locationJson": {
            "name": "Fossá瀑布"
          },
          "detailsJson": {
            "location": "Fossá瀑布",
            "durationHours": 1
          }
        }
      ]
    },
    {
      "dayNumber": 6,
      "title": "达兰加尔门海蚀拱门",
      "summary": "乘船游览壮观的海上石拱门，感受自然奇观。",
      "detailsJson": null,
      "timeSlots": [
        {
          "sequence": 1,
          "durationHours": 3,
          "durationMinutes": 180,
          "type": "cruise",
          "title": "乘船前往达兰加尔门",
          "activityHighlights": {
            "text": "乘船近距离观赏高达70米的天然海蚀拱门，感受北大西洋的磅礴气势。"
          },
          "scenicIntro": "达兰加尔门是法罗群岛最受欢迎的地标之一，是冰川与海水侵蚀的杰作。",
          "locationJson": {
            "name": "瓦加尔岛附近"
          },
          "detailsJson": {
            "location": "瓦加尔岛附近",
            "transport": {
              "mode": "boat"
            },
            "durationHours": 3
          }
        }
      ]
    },
    {
      "dayNumber": 7,
      "title": "沃格岛奇观：入海瀑布与海上悬湖",
      "summary": "游览沃格岛，欣赏法罗群岛标志性的自然奇观。",
      "detailsJson": null,
      "timeSlots": [
        {
          "sequence": 1,
          "durationHours": 3,
          "durationMinutes": 180,
          "type": "sightseeing",
          "title": "沃格岛海岸线探索",
          "activityHighlights": {
            "text": "观赏神奇的入海瀑布和仿佛悬浮于海上的湖泊。"
          },
          "scenicIntro": "法罗群岛的地貌由古老的冰川侵蚀形成，造就了无数令人惊叹的景观。",
          "locationJson": {
            "name": "沃格岛"
          },
          "detailsJson": {
            "location": "沃格岛",
            "transport": {
              "mode": "coach"
            },
            "durationHours": 3
          }
        }
      ]
    },
    {
      "dayNumber": 8,
      "title": "告别法罗，返回哥本哈根",
      "summary": "飞返哥本哈根，为北极段旅程做准备。",
      "detailsJson": null,
      "timeSlots": [
        {
          "sequence": 1,
          "durationHours": 2,
          "durationMinutes": 120,
          "type": "transport",
          "title": "飞返哥本哈根",
          "activityHighlights": null,
          "locationJson": {
            "name": "沃格岛机场 -> 哥本哈根"
          },
          "detailsJson": {
            "location": "沃格岛机场 -> 哥本哈根",
            "transport": {
              "mode": "flight"
            },
            "durationHours": 2
          }
        },
        {
          "sequence": 2,
          "durationHours": 4,
          "durationMinutes": 240,
          "type": "leisure",
          "title": "哥本哈根自由活动",
          "activityHighlights": {
            "text": "可前往新港运河区漫步，或自由购物，休整身心。"
          },
          "locationJson": {
            "name": "哥本哈根"
          },
          "detailsJson": {
            "location": "哥本哈根",
            "durationHours": 4
          }
        }
      ]
    },
    {
      "dayNumber": 9,
      "title": "哥本哈根 -> 奥斯陆",
      "summary": "飞往挪威首都奥斯陆，连接北极门户。",
      "detailsJson": null,
      "timeSlots": [
        {
          "sequence": 1,
          "durationHours": 1,
          "durationMinutes": 60,
          "type": "transport",
          "title": "飞往奥斯陆",
          "activityHighlights": null,
          "locationJson": {
            "name": "哥本哈根 -> 奥斯陆"
          },
          "detailsJson": {
            "location": "哥本哈根 -> 奥斯陆",
            "transport": {
              "mode": "flight"
            },
            "durationHours": 1
          }
        },
        {
          "sequence": 2,
          "durationHours": 2,
          "durationMinutes": 120,
          "type": "sightseeing",
          "title": "奥斯陆城市初览",
          "activityHighlights": {
            "text": "初步探索这座被誉为“世界滑雪之都”的北欧都市。"
          },
          "locationJson": {
            "name": "奥斯陆"
          },
          "detailsJson": {
            "location": "奥斯陆",
            "durationHours": 2
          }
        }
      ]
    },
    {
      "dayNumber": 10,
      "title": "奥斯陆文化与飞往北极",
      "summary": "游览奥斯陆城市精华，傍晚飞往斯瓦尔巴德首府朗伊尔城。",
      "detailsJson": null,
      "timeSlots": [
        {
          "sequence": 1,
          "durationHours": 2,
          "durationMinutes": 120,
          "type": "culture",
          "title": "维格朗雕塑公园",
          "activityHighlights": {
            "text": "欣赏192座描绘人生百态的雕塑，包括著名的《生命之柱》。"
          },
          "scenicIntro": "这是世界上最大的由单一艺术家打造的雕塑公园。",
          "locationJson": {
            "name": "维格朗雕塑公园"
          },
          "detailsJson": {
            "location": "维格朗雕塑公园",
            "durationHours": 2
          }
        },
        {
          "sequence": 2,
          "durationHours": 1.5,
          "durationMinutes": 90,
          "type": "culture",
          "title": "奥斯陆市政厅",
          "activityHighlights": {
            "text": "参观诺贝尔和平奖颁奖典礼举办地，了解挪威历史文化。"
          },
          "locationJson": {
            "name": "奥斯陆市政厅"
          },
          "detailsJson": {
            "location": "奥斯陆市政厅",
            "durationHours": 1.5
          }
        },
        {
          "sequence": 3,
          "durationHours": 3,
          "durationMinutes": 180,
          "type": "transport",
          "title": "飞往朗伊尔城",
          "activityHighlights": {
            "text": "飞行穿越北极圈，抵达世界最北的城镇。"
          },
          "locationJson": {
            "name": "奥斯陆 -> 朗伊尔城"
          },
          "detailsJson": {
            "location": "奥斯陆 -> 朗伊尔城",
            "transport": {
              "mode": "flight"
            },
            "durationHours": 3
          }
        }
      ]
    },
    {
      "dayNumber": 11,
      "title": "朗伊尔城 & 登船启航",
      "summary": "探索北极煤矿小镇，下午登船，航向北极熊的王国。",
      "detailsJson": null,
      "timeSlots": [
        {
          "sequence": 1,
          "durationHours": 2,
          "durationMinutes": 120,
          "type": "sightseeing",
          "title": "朗伊尔城探索",
          "activityHighlights": {
            "text": "参观小镇博物馆或北极探险相关纪念地，感受极地生活。"
          },
          "scenicIntro": "朗伊尔城（北纬78度）是世界上最北的人类居住地之一。",
          "locationJson": {
            "name": "朗伊尔城"
          },
          "detailsJson": {
            "location": "朗伊尔城",
            "durationHours": 2
          }
        },
        {
          "sequence": 2,
          "durationHours": 3,
          "durationMinutes": 180,
          "type": "transport",
          "title": "登船与安全演习",
          "activityHighlights": {
            "text": "办理登船手续，参加强制性安全演习和北极熊防护培训。"
          },
          "locationJson": {
            "name": "朗伊尔城码头"
          },
          "detailsJson": {
            "location": "朗伊尔城码头",
            "transport": {
              "mode": "ship"
            },
            "durationHours": 3
          }
        },
        {
          "sequence": 3,
          "durationHours": 2,
          "durationMinutes": 120,
          "type": "cruise",
          "title": "启航进入冰原",
          "activityHighlights": {
            "text": "船只缓缓驶出峡湾，开始真正的北极探险。"
          },
          "locationJson": {
            "name": "伊斯峡湾"
          },
          "detailsJson": {
            "location": "伊斯峡湾",
            "durationHours": 2
          }
        }
      ]
    },
    {
      "dayNumber": 12,
      "title": "斯瓦尔巴德西部峡湾探索",
      "summary": "根据冰情与天气，开始首次登陆或巡游，寻觅野生动物。",
      "detailsJson": null,
      "timeSlots": [
        {
          "sequence": 1,
          "durationHours": 3,
          "durationMinutes": 180,
          "type": "nature",
          "title": "首次橡皮艇巡游/登陆",
          "activityHighlights": {
            "text": "在探险队带领下，寻找海象、驯鹿的踪迹，观察丰富的苔原植物。"
          },
          "scenicIntro": "斯瓦尔巴德的峡湾在夏季充满生机。",
          "locationJson": {
            "name": "如Bellsund或Van Keulenfjorden"
          },
          "detailsJson": {
            "location": "如Bellsund或Van Keulenfjorden",
            "durationHours": 3
          }
        },
        {
          "sequence": 2,
          "durationHours": 1.5,
          "durationMinutes": 90,
          "type": "education",
          "title": "北极生态讲座",
          "activityHighlights": {
            "text": "学习关于北极熊、海象、斯瓦尔巴德驯鹿等野生动物的知识。"
          },
          "locationJson": {
            "name": "船上讲座室"
          },
          "detailsJson": {
            "location": "船上讲座室",
            "durationHours": 1.5
          }
        }
      ]
    },
    {
      "dayNumber": 13,
      "title": "向东北航行，穿越北纬80度",
      "summary": "向斯瓦尔巴德更偏远、冰况更好的东北部地区进发，增加发现北极熊的机会。",
      "detailsJson": null,
      "timeSlots": [
        {
          "sequence": 1,
          "durationHours": 8,
          "durationMinutes": 480,
          "type": "nature",
          "title": "甲板守望与航行",
          "activityHighlights": {
            "text": "在甲板上用望远镜持续扫描海冰与海岸，寻找北极熊、北极狐的踪迹。"
          },
          "locationJson": {
            "name": "斯瓦尔巴德北部海域"
          },
          "detailsJson": {
            "localTip": "穿戴保暖，防风是甲板观测的关键。双筒望远镜为必备。",
            "location": "斯瓦尔巴德北部海域",
            "durationHours": 8
          }
        },
        {
          "sequence": 2,
          "durationHours": 1,
          "durationMinutes": 60,
          "type": "community",
          "title": "穿越北纬80度仪式",
          "activityHighlights": {
            "text": "举行小型庆祝仪式，纪念抵达地球顶端附近的非凡纬度。"
          },
          "locationJson": null,
          "detailsJson": {
            "durationHours": 1
          }
        }
      ]
    },
    {
      "dayNumber": 14,
      "title": "北极核心区：七岛群岛",
      "summary": "探索斯瓦尔巴德最北端的群岛，这里是北极熊和海象的重要栖息地。",
      "detailsJson": null,
      "timeSlots": [
        {
          "sequence": 1,
          "durationHours": 2,
          "durationMinutes": 120,
          "type": "cruise",
          "title": "Phippsøya岛附近巡游",
          "activityHighlights": {
            "text": "橡皮艇巡游于浮冰之间，在世界上最北的陆地之一寻找北极熊。"
          },
          "scenicIntro": "七岛群岛是斯瓦尔巴德最北的陆地，几乎终年被海冰覆盖。",
          "locationJson": {
            "name": "七岛群岛"
          },
          "detailsJson": {
            "location": "七岛群岛",
            "durationHours": 2
          }
        },
        {
          "sequence": 2,
          "durationHours": 3,
          "durationMinutes": 180,
          "type": "nature",
          "title": "冰上观测",
          "activityHighlights": {
            "text": "船只在海冰边缘缓慢航行，探险队员和专业向导在船头集中观测。"
          },
          "locationJson": null,
          "detailsJson": {
            "durationHours": 3
          }
        }
      ]
    },
    {
      "dayNumber": 15,
      "title": "Hinlopen海峡与北极鸟崖",
      "summary": "穿越雄伟的Hinlopen海峡，参观巨大的海鸟悬崖。",
      "detailsJson": null,
      "timeSlots": [
        {
          "sequence": 1,
          "durationHours": 2,
          "durationMinutes": 120,
          "type": "nature",
          "title": "Alkefjellet鸟崖巡游",
          "activityHighlights": {
            "text": "乘橡皮艇近距离观赏由数十万只厚嘴海鸦筑巢的玄武岩悬崖，景象和声音都极为震撼。"
          },
          "scenicIntro": "Alkefjellet是北极地区最重要的海鸟繁殖地之一。",
          "locationJson": {
            "name": "Hinlopen海峡"
          },
          "detailsJson": {
            "location": "Hinlopen海峡",
            "durationHours": 2
          }
        },
        {
          "sequence": 2,
          "durationHours": 3,
          "durationMinutes": 180,
          "type": "hiking",
          "title": "海峡东侧登陆",
          "activityHighlights": {
            "text": "在苔原上徒步，有机会邂逅北极狐，观察古老的捕鲸者遗迹。"
          },
          "locationJson": {
            "name": "如Augustabukta"
          },
          "detailsJson": {
            "location": "如Augustabukta",
            "durationHours": 3
          }
        }
      ]
    },
    {
      "dayNumber": 16,
      "title": "东北地岛与冰瀑布",
      "summary": "探访斯瓦尔巴德最大的岛屿，寻找行程亮点之一的超级冰川与冰瀑布。",
      "detailsJson": null,
      "timeSlots": [
        {
          "sequence": 1,
          "durationHours": 3,
          "durationMinutes": 180,
          "type": "cruise",
          "title": "巡游200公里长超级冰川前沿",
          "activityHighlights": {
            "text": "船只沿巨大的冰川前沿巡游，亲眼目睹绵延不绝的冰墙和飞泻而下的冰瀑布。"
          },
          "scenicIntro": "这是斯瓦尔巴德乃至整个北极地区最壮观的冰川景观之一。",
          "locationJson": {
            "name": "东北地岛冰盖前沿"
          },
          "detailsJson": {
            "location": "东北地岛冰盖前沿",
            "durationHours": 3
          }
        },
        {
          "sequence": 2,
          "durationHours": 1.5,
          "durationMinutes": 90,
          "type": "education",
          "title": "冰川学讲座",
          "activityHighlights": {
            "text": "由地质学家或冰川学家讲解冰川的形成、运动与对气候的影响。"
          },
          "locationJson": null,
          "detailsJson": {
            "durationHours": 1.5
          }
        }
      ]
    },
    {
      "dayNumber": 17,
      "title": "西北斯匹次卑尔根国家公园",
      "summary": "探索受保护的国家公园，这里拥有深邃的峡湾和丰富的历史遗迹。",
      "detailsJson": null,
      "timeSlots": [
        {
          "sequence": 1,
          "durationHours": 2,
          "durationMinutes": 120,
          "type": "history",
          "title": "Magdalenefjord峡湾登陆",
          "activityHighlights": {
            "text": "参观17世纪捕鲸者的墓地与遗迹，在美丽的海滩漫步。"
          },
          "scenicIntro": "这个峡湾是早期北极探险的重要基地，风景如画。",
          "locationJson": {
            "name": "Magdalenefjord"
          },
          "detailsJson": {
            "location": "Magdalenefjord",
            "durationHours": 2
          }
        },
        {
          "sequence": 2,
          "durationHours": 2,
          "durationMinutes": 120,
          "type": "cruise",
          "title": "峡湾巡游与野生动物观测",
          "activityHighlights": {
            "text": "继续在峡湾中寻找髯海豹、环斑海豹和岸边可能出现的北极熊。"
          },
          "locationJson": null,
          "detailsJson": {
            "durationHours": 2
          }
        }
      ]
    },
    {
      "dayNumber": 18,
      "title": "斯瓦尔巴德最后探索",
      "summary": "根据最佳天气和动物踪迹，选择最后一个精彩的登陆点。",
      "detailsJson": null,
      "timeSlots": [
        {
          "sequence": 1,
          "durationHours": 3,
          "durationMinutes": 180,
          "type": "nature",
          "title": "最后一次斯瓦尔巴德登陆/巡游",
          "activityHighlights": {
            "text": "珍惜在北极熊王国的最后时光，可能是苔原徒步、历史遗迹探访或最后的北极熊守望。"
          },
          "locationJson": {
            "name": "由探险队长决定"
          },
          "detailsJson": {
            "location": "由探险队长决定",
            "durationHours": 3
          }
        },
        {
          "sequence": 2,
          "durationHours": 2,
          "durationMinutes": 120,
          "type": "cruise",
          "title": "航向朗伊尔城",
          "activityHighlights": {
            "text": "开始返航，在船上回顾和整理斯瓦尔巴德的照片与笔记。"
          },
          "locationJson": null,
          "detailsJson": {
            "durationHours": 2
          }
        }
      ]
    },
    {
      "dayNumber": 19,
      "title": "下船 & 飞返奥斯陆",
      "summary": "清晨抵达朗伊尔城，下船后飞返挪威大陆。",
      "detailsJson": null,
      "timeSlots": [
        {
          "sequence": 1,
          "durationHours": 1.5,
          "durationMinutes": 90,
          "type": "departure",
          "title": "下船与告别探险队",
          "activityHighlights": {
            "text": "与共度多日的探险队员和船员告别。"
          },
          "locationJson": {
            "name": "朗伊尔城码头"
          },
          "detailsJson": {
            "location": "朗伊尔城码头",
            "durationHours": 1.5
          }
        },
        {
          "sequence": 2,
          "durationHours": 3,
          "durationMinutes": 180,
          "type": "transport",
          "title": "飞返奥斯陆",
          "activityHighlights": null,
          "locationJson": {
            "name": "朗伊尔城 -> 奥斯陆"
          },
          "detailsJson": {
            "location": "朗伊尔城 -> 奥斯陆",
            "transport": {
              "mode": "flight"
            },
            "durationHours": 3
          }
        }
      ]
    },
    {
      "dayNumber": 20,
      "title": "奥斯陆 -> 中国（夜宿航班）",
      "summary": "前往机场，搭乘国际航班返回中国。",
      "detailsJson": null,
      "timeSlots": [
        {
          "sequence": 1,
          "durationHours": 2,
          "durationMinutes": 120,
          "type": "departure",
          "title": "机场送机与返程",
          "activityHighlights": {
            "text": "办理登机手续，带着北大西洋与北极的双重记忆踏上归途。"
          },
          "locationJson": {
            "name": "奥斯陆机场"
          },
          "detailsJson": {
            "location": "奥斯陆机场",
            "transport": {
              "mode": "private_transfer"
            },
            "durationHours": 2
          }
        }
      ]
    },
    {
      "dayNumber": 21,
      "title": "跨洋飞行",
      "summary": "在航班上度过，回味旅程。",
      "detailsJson": null,
      "timeSlots": [
        {
          "sequence": 1,
          "durationHours": 24,
          "durationMinutes": 1440,
          "type": "transport",
          "title": "国际航班",
          "activityHighlights": {
            "text": "休息调整，整理思绪。"
          },
          "locationJson": {
            "name": "国际航班"
          },
          "detailsJson": {
            "location": "国际航班",
            "transport": {
              "mode": "flight"
            },
            "durationHours": 24
          }
        }
      ]
    },
    {
      "dayNumber": 22,
      "title": "抵达中国",
      "summary": "抵达国内，圆满结束法罗群岛与斯瓦尔巴德的深度探索之旅。",
      "detailsJson": null,
      "timeSlots": [
        {
          "sequence": 1,
          "durationHours": 1,
          "durationMinutes": 60,
          "type": "departure",
          "title": "抵达与解散",
          "activityHighlights": {
            "text": "抵达国内机场，提取行李，与同行旅伴告别，行程结束。"
          },
          "locationJson": {
            "name": "国内机场"
          },
          "detailsJson": {
            "location": "国内机场",
            "durationHours": 1
          }
        }
      ]
    }
  ]
}